{"stats":{"minecraft:custom":{"minecraft:jump":340,"minecraft:time_since_rest":10837,"minecraft:damage_taken":260,"minecraft:leave_game":3,"minecraft:crouch_one_cm":496,"minecraft:time_since_death":10808,"minecraft:play_time":23785,"minecraft:sprint_one_cm":8638,"minecraft:walk_one_cm":3741,"minecraft:walk_on_water_one_cm":11509,"minecraft:deaths":1,"minecraft:sneak_time":2325,"minecraft:total_world_time":23785,"minecraft:climb_one_cm":58472,"minecraft:walk_under_water_one_cm":20777,"minecraft:fall_one_cm":4083,"minecraft:fly_one_cm":1652612},"minecraft:picked_up":{"minecraft:scaffolding":2,"minecraft:cobblestone":1},"minecraft:mined":{"minecraft:stone":1},"minecraft:used":{"minecraft:diamond_pickaxe":1,"minecraft:stone":2,"minecraft:scaffolding":262}},"DataVersion":3120}