{"stats":{"minecraft:used":{"minecraft:jungle_boat":1,"minecraft:wooden_axe":8,"minecraft:crafting_table":1},"minecraft:custom":{"minecraft:time_since_rest":3917,"minecraft:play_time":3917,"minecraft:sprint_one_cm":11170,"minecraft:walk_one_cm":2395,"minecraft:boat_one_cm":6330,"minecraft:jump":140,"minecraft:leave_game":1,"minecraft:time_since_death":3917,"minecraft:total_world_time":3917,"minecraft:climb_one_cm":182,"minecraft:fall_one_cm":4238,"minecraft:interact_with_crafting_table":3,"minecraft:fly_one_cm":46575},"minecraft:crafted":{"minecraft:crafting_table":1,"minecraft:stick":4,"minecraft:jungle_boat":1,"minecraft:wooden_pickaxe":1,"minecraft:jungle_planks":40,"minecraft:wooden_axe":1},"minecraft:mined":{"minecraft:jungle_log":10,"minecraft:crafting_table":1},"minecraft:picked_up":{"minecraft:crafting_table":1,"minecraft:jungle_log":10}},"DataVersion":3120}